LICENSE
README.md
setup.cfg
setup.py
arbitragerepair/__init__.py
arbitragerepair/constraints.py
arbitragerepair/repair.py
arbitragerepair.egg-info/PKG-INFO
arbitragerepair.egg-info/SOURCES.txt
arbitragerepair.egg-info/dependency_links.txt
arbitragerepair.egg-info/requires.txt
arbitragerepair.egg-info/top_level.txt