Metadata-Version: 2.1
Name: arbitragerepair
Version: 1.1.0
Summary: Model-free algorithms of detecting and repairing spread, butterfly and calendar arbitrages in European option prices.
Home-page: https://github.com/vicaws/arbitragerepair
Author: Victor Wang
Author-email: wangsheng.victor@gmail.com
License: MIT
Keywords: option,arbitrage,quantitative finance,data cleansing,asset pricing
Classifier: Programming Language :: Python :: 3
Classifier: License :: OSI Approved :: MIT License
License-File: LICENSE
Requires-Dist: cvxopt>=1.3.0
Requires-Dist: numpy>=1.19.0
Requires-Dist: pandas>=1.0.5
